thumbalizr.py
Thumbalizr-1.0.1.dist-info/METADATA
Thumbalizr-1.0.1.dist-info/WHEEL
Thumbalizr-1.0.1.dist-info/top_level.txt
Thumbalizr-1.0.1.dist-info/RECORD
