Metadata-Version: 2.1
Name: Thumbalizr
Version: 1.0.1
Summary: Client to interact with Thumbalizr
Home-page: https://github.com/juliensobrier/thumbalizr-python
Author: Julien Sobrier
Author-email: julien@sobrier.net
License: Apache
Platform: UNKNOWN
Classifier: Development Status :: 4 - Beta
Classifier: Environment :: Console
Classifier: Intended Audience :: Developers
Classifier: Intended Audience :: Information Technology
Classifier: License :: OSI Approved :: BSD License
Classifier: Operating System :: OS Independent
Classifier: Programming Language :: Python
Requires-Dist: hashlib
Requires-Dist: requests
